mistral_inference/__init__.py
mistral_inference/args.py
mistral_inference/cache.py
mistral_inference/generate.py
mistral_inference/lora.py
mistral_inference/main.py
mistral_inference/mamba.py
mistral_inference/model.py
mistral_inference/moe.py
mistral_inference/rope.py
mistral_inference/transformer.py
mistral_inference/transformer_layers.py
mistral_inference/vision_encoder.py
mistral_inference-1.6.0.dist-info/LICENSE
mistral_inference-1.6.0.dist-info/METADATA
mistral_inference-1.6.0.dist-info/WHEEL
mistral_inference-1.6.0.dist-info/entry_points.txt
mistral_inference-1.6.0.dist-info/RECORD
