Metadata-Version: 2.3
Name: mistral_inference
Version: 1.6.0
Summary: 
Author: bam4d
Author-email: bam4d@mistral.ai
Requires-Python: >=3.9.10,<4.0.0
Classifier: Programming Language :: Python :: 3
Classifier: Programming Language :: Python :: 3.10
Classifier: Programming Language :: Python :: 3.11
Classifier: Programming Language :: Python :: 3.12
Classifier: Programming Language :: Python :: 3.13
Requires-Dist: fire (>=0.6.0)
Requires-Dist: mistral_common (>=1.5.4)
Requires-Dist: pillow (>=10.3.0)
Requires-Dist: safetensors (>=0.4.0)
Requires-Dist: simple-parsing (>=0.1.5)
Requires-Dist: xformers (>=0.0.24)
